<?xml version="1.0" encoding="UTF-8"?>
<!-- All quantities are in Hartree atomic units unless otherwise specified -->
<qes:espresso xmlns:xsi="http://www.w3.org/2001/XMLSchema-instance" xmlns:qes="http://www.quantum-espresso.org/ns/qes/qes-1.0" xsi:schemaLocation="http://www.quantum-espresso.org/ns/qes/qes-1.0 http://www.quantum-espresso.org/ns/qes/qes_230310.xsd" Units="Hartree atomic units">
  <general_info>
    <xml_format NAME="QEXSD" VERSION="23.03.10">QEXSD_23.03.10</xml_format>
    <creator NAME="PWSCF" VERSION="7.3.1">XML file generated by PWSCF</creator>
    <created DATE="15Mar2025" TIME="23:22: 4">This run was terminated on:  23:22: 4  15 Mar 2025</created>
    <job></job>
  </general_info>
  <parallel_info>
    <nprocs>30</nprocs>
    <nthreads>1</nthreads>
    <ntasks>1</ntasks>
    <nbgrp>1</nbgrp>
    <npool>1</npool>
    <ndiag>30</ndiag>
  </parallel_info>
  <input>
    <control_variables>
      <title></title>
      <calculation>relax</calculation>
      <restart_mode>from_scratch</restart_mode>
      <prefix>H2O</prefix>
      <pseudo_dir>/home/ys/qepseudo/SSSP_1.3.0_PBE_efficiency</pseudo_dir>
      <outdir>./tmp</outdir>
      <stress>true</stress>
      <forces>true</forces>
      <wf_collect>true</wf_collect>
      <disk_io>low</disk_io>
      <max_seconds>172800</max_seconds>
      <nstep>100</nstep>
      <etot_conv_thr>5.000000000000000E-006</etot_conv_thr>
      <forc_conv_thr>2.500000000000000E-004</forc_conv_thr>
      <press_conv_thr>5.000000000000000E-001</press_conv_thr>
      <verbosity>high</verbosity>
      <print_every>100000</print_every>
      <fcp>false</fcp>
      <rism>false</rism>
    </control_variables>
    <atomic_species ntyp="2">
      <species name="O">
        <mass>1.599940000000000E+001</mass>
        <pseudo_file>O.pbe-n-kjpaw_psl.0.1.UPF</pseudo_file>
      </species>
      <species name="H">
        <mass>1.007940000000000E+000</mass>
        <pseudo_file>H.pbe-rrkjus_psl.1.0.0.UPF</pseudo_file>
      </species>
    </atomic_species>
    <atomic_structure nat="3" alat="28.345891869386552" bravais_index="1">
      <atomic_positions>
        <atom name="O" index="1">
  8.042920050803479E-001  1.892904643967391E+000  2.223247667813222E+000
        </atom>
        <atom name="H" index="2">2.628644944150814E+000  1.842724856454078E+000  2.134740455040249E+000</atom>
        <atom name="H" index="3">2.920722903699098E-001  1.027812590553333E+000  6.974695667075024E-001</atom>
      </atomic_positions>
      <cell>
        <a1>2.834589186938655E+001  0.000000000000000E+000  0.000000000000000E+000</a1>
        <a2>0.000000000000000E+000  2.834589186938655E+001  0.000000000000000E+000</a2>
        <a3>0.000000000000000E+000  0.000000000000000E+000  2.834589186938655E+001</a3>
      </cell>
    </atomic_structure>
    <dft>
      <functional>PBE</functional>
    </dft>
    <spin>
      <lsda>false</lsda>
      <noncolin>false</noncolin>
      <spinorbit>false</spinorbit>
    </spin>
    <bands>
      <smearing degauss="1.0000000000000000E-002">mv</smearing>
      <tot_charge>0.000000000000000E+000</tot_charge>
      <occupations>smearing</occupations>
    </bands>
    <basis>
      <gamma_only>true</gamma_only>
      <ecutwfc>1.500000000000000E+001</ecutwfc>
      <ecutrho>6.000000000000000E+001</ecutrho>
    </basis>
    <electron_control>
      <diagonalization>davidson</diagonalization>
      <mixing_mode>plain</mixing_mode>
      <mixing_beta>7.000000000000000E-001</mixing_beta>
      <conv_thr>3.675000000000000E-007</conv_thr>
      <mixing_ndim>8</mixing_ndim>
      <max_nstep>200</max_nstep>
      <exx_nstep>100</exx_nstep>
      <real_space_q>false</real_space_q>
      <real_space_beta>false</real_space_beta>
      <tq_smoothing>false</tq_smoothing>
      <tbeta_smoothing>false</tbeta_smoothing>
      <diago_thr_init>0.000000000000000E+000</diago_thr_init>
      <diago_full_acc>false</diago_full_acc>
      <diago_cg_maxiter>20</diago_cg_maxiter>
      <diago_ppcg_maxiter>20</diago_ppcg_maxiter>
      <diago_rmm_ndim>4</diago_rmm_ndim>
      <diago_gs_nblock>16</diago_gs_nblock>
      <diago_rmm_conv>false</diago_rmm_conv>
    </electron_control>
    <k_points_IBZ>
      <nk>1</nk>
      <k_point weight="1.0000000000000000">0.000000000000000E+000  0.000000000000000E+000  0.000000000000000E+000</k_point>
    </k_points_IBZ>
    <ion_control>
      <ion_dynamics>bfgs</ion_dynamics>
      <upscale>1.000000000000000E+002</upscale>
      <remove_rigid_rot>false</remove_rigid_rot>
      <refold_pos>false</refold_pos>
      <bfgs>
        <ndim>1</ndim>
        <trust_radius_min>1.000000000000000E-004</trust_radius_min>
        <trust_radius_max>8.000000000000000E-001</trust_radius_max>
        <trust_radius_init>5.000000000000000E-001</trust_radius_init>
        <w1>1.000000000000000E-002</w1>
        <w2>5.000000000000000E-001</w2>
      </bfgs>
    </ion_control>
    <cell_control>
      <cell_dynamics>none</cell_dynamics>
      <pressure>0.000000000000000E+000</pressure>
      <wmass>0.000000000000000E+000</wmass>
      <cell_do_free>all</cell_do_free>
    </cell_control>
    <symmetry_flags>
      <nosym>true</nosym>
      <nosym_evc>false</nosym_evc>
      <noinv>false</noinv>
      <no_t_rev>false</no_t_rev>
      <force_symmorphic>false</force_symmorphic>
      <use_all_frac>false</use_all_frac>
    </symmetry_flags>
    <free_positions rank="2" dims="           3           3">
           1           1           1
           1           1           1
           1           1           1
    </free_positions>
  </input>
  <step>
    <scf_conv>
      <convergence_achieved>true</convergence_achieved>
      <n_scf_steps>7</n_scf_steps>
      <scf_error>3.582165023829118E-007</scf_error>
    </scf_conv>
    <atomic_structure nat="3" alat="28.345891869386552">
      <atomic_positions>
        <atom name="O" index="1">
  8.042920050803479E-001  1.892904643967391E+000  2.223247667813222E+000
        </atom>
        <atom name="H" index="2">2.628644944150814E+000  1.842724856454078E+000  2.134740455040249E+000</atom>
        <atom name="H" index="3">2.920722903699098E-001  1.027812590553333E+000  6.974695667075024E-001</atom>
      </atomic_positions>
      <cell>
        <a1>2.834589186938655E+001  0.000000000000000E+000  0.000000000000000E+000</a1>
        <a2>0.000000000000000E+000  2.834589186938655E+001  0.000000000000000E+000</a2>
        <a3>0.000000000000000E+000  0.000000000000000E+000  2.834589186938655E+001</a3>
      </cell>
    </atomic_structure>
    <total_energy>
      <etot>-2.198441778013783E+001</etot>
      <eband>-4.052109064286165E+000</eband>
      <ehart>1.807701390078444E+001</ehart>
      <vtxc>-5.502372348466448E+000</vtxc>
      <etxc>-4.411991437663430E+000</etxc>
      <ewald>3.718230180444264E+000</ewald>
      <demet>2.411815794571846E-019</demet>
    </total_energy>
    <forces rank="2" dims="           3           3">
 -6.441245799684892E-003  4.532101064460913E-003  8.087003617269883E-003
  1.134379128329979E-002  5.762001156431759E-004  1.031008825867831E-003
 -4.902545483614899E-003 -5.108301180104089E-003 -9.118012443137716E-003
    </forces>
    <stress rank="2" dims="           3           3">
 -6.536106784881312E-006  2.409907591640151E-007  4.272057778667427E-007
  2.409907591640151E-007 -8.058125543212643E-006  6.671116495252237E-007
  4.272057778667427E-007  6.671116495252237E-007 -7.259689944413422E-006
    </stress>
  </step>
  <step>
    <scf_conv>
      <convergence_achieved>true</convergence_achieved>
      <n_scf_steps>5</n_scf_steps>
      <scf_error>1.470768237502503E-008</scf_error>
    </scf_conv>
    <atomic_structure nat="3" alat="28.345891869386552">
      <atomic_positions>
        <atom name="O" index="1">
  7.914095134809782E-001  1.901968846096313E+000  2.239421675047762E+000
        </atom>
        <atom name="H" index="2">2.651332526717414E+000  1.843877256685365E+000  2.136802472691985E+000</atom>
        <atom name="H" index="3">2.822671994026800E-001  1.017595988193125E+000  6.792335418212270E-001</atom>
      </atomic_positions>
      <cell>
        <a1>2.834589186938655E+001  0.000000000000000E+000  0.000000000000000E+000</a1>
        <a2>0.000000000000000E+000  2.834589186938655E+001  0.000000000000000E+000</a2>
        <a3>0.000000000000000E+000  0.000000000000000E+000  2.834589186938655E+001</a3>
      </cell>
    </atomic_structure>
    <total_energy>
      <etot>-2.198455051806187E+001</etot>
      <eband>-4.020200101671374E+000</eband>
      <ehart>1.797197680794160E+001</ehart>
      <vtxc>-5.479574438276844E+000</vtxc>
      <etxc>-4.394495623495065E+000</etxc>
      <ewald>3.584069026279000E+000</ewald>
      <demet>1.329564512415744E-019</demet>
    </total_energy>
    <forces rank="2" dims="           3           3">
  5.875985786014729E-003 -4.177611768620201E-003 -7.339239193342703E-003
 -5.755358390415283E-003  1.052834666259073E-003  1.906724697995271E-003
 -1.206273955994463E-004  3.124777102361128E-003  5.432514495347431E-003
    </forces>
    <stress rank="2" dims="           3           3">
 -7.867147268346285E-006  1.006259239894122E-007  1.817864730512931E-007
  1.006259239894122E-007 -8.300088000038712E-006  1.514230892292798E-007
  1.817864730512931E-007  1.514230892292798E-007 -8.119145276168328E-006
    </stress>
  </step>
  <step>
    <scf_conv>
      <convergence_achieved>true</convergence_achieved>
      <n_scf_steps>5</n_scf_steps>
      <scf_error>4.459161343963538E-009</scf_error>
    </scf_conv>
    <atomic_structure nat="3" alat="28.345891869386552">
      <atomic_positions>
        <atom name="O" index="1">
  7.982599090730174E-001  1.897095616835217E+000  2.230867884198848E+000
        </atom>
        <atom name="H" index="2">2.644925298092323E+000  1.845208655436124E+000  2.139212935984021E+000</atom>
        <atom name="H" index="3">2.818240324357316E-001  1.021137818703461E+000  6.853768693781045E-001</atom>
      </atomic_positions>
      <cell>
        <a1>2.834589186938655E+001  0.000000000000000E+000  0.000000000000000E+000</a1>
        <a2>0.000000000000000E+000  2.834589186938655E+001  0.000000000000000E+000</a2>
        <a3>0.000000000000000E+000  0.000000000000000E+000  2.834589186938655E+001</a3>
      </cell>
    </atomic_structure>
    <total_energy>
      <etot>-2.198466808898117E+001</etot>
      <eband>-4.031429262883614E+000</eband>
      <ehart>1.801183169386020E+001</ehart>
      <vtxc>-5.488193860366202E+000</vtxc>
      <etxc>-4.401109001308254E+000</etxc>
      <ewald>3.634050381502892E+000</ewald>
      <demet>1.730603763152769E-019</demet>
    </total_energy>
    <forces rank="2" dims="           3           3">
  9.380419240108567E-004 -6.991824885685309E-004 -1.171520556983974E-003
  3.000194122133449E-004  5.948192641057181E-004  1.078682389448116E-003
 -1.238061336224202E-003  1.043632244628129E-004  9.283816753585820E-005
    </forces>
    <stress rank="2" dims="           3           3">
 -7.403838539485891E-006  1.293269914594613E-007  2.307198229731855E-007
  1.293269914594613E-007 -8.205908059806968E-006  3.427620134992658E-007
  2.307198229731855E-007  3.427620134992658E-007 -7.795386509248336E-006
    </stress>
  </step>
  <step>
    <scf_conv>
      <convergence_achieved>true</convergence_achieved>
      <n_scf_steps>4</n_scf_steps>
      <scf_error>6.229524610141596E-009</scf_error>
    </scf_conv>
    <atomic_structure nat="3" alat="28.345891869386552">
      <atomic_positions>
        <atom name="O" index="1">
  8.002260677150412E-001  1.895623087740052E+000  2.228414383246349E+000
        </atom>
        <atom name="H" index="2">2.645976353306171E+000  1.846601667698792E+000  2.141738363665588E+000</atom>
        <atom name="H" index="3">2.788068185798598E-001  1.021217335535958E+000  6.853049426490364E-001</atom>
      </atomic_positions>
      <cell>
        <a1>2.834589186938655E+001  0.000000000000000E+000  0.000000000000000E+000</a1>
        <a2>0.000000000000000E+000  2.834589186938655E+001  0.000000000000000E+000</a2>
        <a3>0.000000000000000E+000  0.000000000000000E+000  2.834589186938655E+001</a3>
      </cell>
    </atomic_structure>
    <total_energy>
      <etot>-2.198467842893740E+001</etot>
      <eband>-4.032128722632336E+000</eband>
      <ehart>1.801560387379422E+001</ehart>
      <vtxc>-5.489019926294724E+000</vtxc>
      <etxc>-4.401744040251129E+000</etxc>
      <ewald>3.637938187737010E+000</ewald>
      <demet>1.727375684800718E-019</demet>
    </total_energy>
    <forces rank="2" dims="           3           3">
  2.596182703285488E-004 -2.087035594390196E-004 -2.916427978365499E-004
  6.520386939977352E-004  3.628357003252385E-004  6.647578620391254E-004
 -9.116569643262839E-004 -1.541321408862189E-004 -3.731150642025756E-004
    </forces>
    <stress rank="2" dims="           3           3">
 -7.377852174963286E-006  1.162839257108161E-007  2.072725757493326E-007
  1.162839257108161E-007 -8.186058572114226E-006  3.587466704592312E-007
  2.072725757493326E-007  3.587466704592312E-007 -7.755886097354897E-006
    </stress>
  </step>
  <step>
    <scf_conv>
      <convergence_achieved>true</convergence_achieved>
      <n_scf_steps>3</n_scf_steps>
      <scf_error>8.257799180495926E-009</scf_error>
    </scf_conv>
    <atomic_structure nat="3" alat="28.345891869386552">
      <atomic_positions>
        <atom name="O" index="1">
  8.018882359078847E-001  1.894349437180281E+000  2.226439612619817E+000
        </atom>
        <atom name="H" index="2">2.647975525087852E+000  1.848164700863175E+000  2.144592365032051E+000</atom>
        <atom name="H" index="3">2.751454786053349E-001  1.020927952931347E+000  6.844257119091054E-001</atom>
      </atomic_positions>
      <cell>
        <a1>2.834589186938655E+001  0.000000000000000E+000  0.000000000000000E+000</a1>
        <a2>0.000000000000000E+000  2.834589186938655E+001  0.000000000000000E+000</a2>
        <a3>0.000000000000000E+000  0.000000000000000E+000  2.834589186938655E+001</a3>
      </cell>
    </atomic_structure>
    <total_energy>
      <etot>-2.198468440787966E+001</etot>
      <eband>-4.031217781983912E+000</eband>
      <ehart>1.801468842323172E+001</ehart>
      <vtxc>-5.488808799884961E+000</vtxc>
      <etxc>-4.401580412028547E+000</etxc>
      <ewald>3.636804722726284E+000</ewald>
      <demet>1.776833051002075E-019</demet>
    </total_energy>
    <forces rank="2" dims="           3           3">
 -6.943213486625661E-005 -1.860189290874945E-005  5.921564919318127E-005
  4.295705618441579E-004  1.261335118275808E-004  2.391639604873089E-004
 -3.601384269779014E-004 -1.075316189188313E-004 -2.983796096804902E-004
    </forces>
    <stress rank="2" dims="           3           3">
 -7.422235504999899E-006  9.639966185281771E-008  1.720609717765526E-007
  9.639966185281771E-008 -8.202077056406890E-006  3.567340562685786E-007
  1.720609717765526E-007  3.567340562685786E-007 -7.773748340192211E-006
    </stress>
  </step>
  <step>
    <scf_conv>
      <convergence_achieved>true</convergence_achieved>
      <n_scf_steps>4</n_scf_steps>
      <scf_error>1.355473042162554E-010</scf_error>
    </scf_conv>
    <atomic_structure nat="3" alat="28.345891869386552">
      <atomic_positions>
        <atom name="O" index="1">
  8.025419650974656E-001  1.893648971888091E+000  2.225552819226879E+000
        </atom>
        <atom name="H" index="2">2.649448589023877E+000  1.849057772399800E+000  2.146246740130446E+000</atom>
        <atom name="H" index="3">2.730186854797300E-001  1.020735346686912E+000  6.836581302036492E-001</atom>
      </atomic_positions>
      <cell>
        <a1>2.834589186938655E+001  0.000000000000000E+000  0.000000000000000E+000</a1>
        <a2>0.000000000000000E+000  2.834589186938655E+001  0.000000000000000E+000</a2>
        <a3>0.000000000000000E+000  0.000000000000000E+000  2.834589186938655E+001</a3>
      </cell>
    </atomic_structure>
    <total_energy>
      <etot>-2.198468545540472E+001</etot>
      <eband>-4.030511212499176E+000</eband>
      <ehart>1.801317647863582E+001</ehart>
      <vtxc>-5.488483420298243E+000</vtxc>
      <etxc>-4.401331028004509E+000</etxc>
      <ewald>3.634309867773721E+000</ewald>
      <demet>1.737615422746113E-019</demet>
    </total_energy>
    <forces rank="2" dims="           3           3">
  2.933750968339834E-008  4.639012079194125E-006  9.652194447241056E-005
 -3.617570358064769E-006 -5.254505344260721E-006  9.524991690917006E-006
  3.588232848381364E-006  6.154932650665894E-007 -1.060469361633276E-004
    </forces>
    <stress rank="2" dims="           3           3">
 -7.457377763580203E-006  8.394997106690246E-008  1.498689038721183E-007
  8.394997106690246E-008 -8.198200262546284E-006  3.492747125257142E-007
  1.498689038721183E-007  3.492747125257142E-007 -7.778292165848453E-006
    </stress>
  </step>
  <output>
    <convergence_info>
      <scf_conv>
        <convergence_achieved>true</convergence_achieved>
        <n_scf_steps>4</n_scf_steps>
        <scf_error>6.777365210812768E-011</scf_error>
      </scf_conv>
      <opt_conv>
        <convergence_achieved>true</convergence_achieved>
        <n_opt_steps>5</n_opt_steps>
        <grad_norm>2.879488571498651E-004</grad_norm>
      </opt_conv>
    </convergence_info>
    <algorithmic_info>
      <real_space_q>false</real_space_q>
      <real_space_beta>false</real_space_beta>
      <uspp>true</uspp>
      <paw>true</paw>
    </algorithmic_info>
    <atomic_species ntyp="2" pseudo_dir="/home/ys/qepseudo/SSSP_1.3.0_PBE_efficiency/">
      <species name="O">
        <mass>1.599940000000000E+001</mass>
        <pseudo_file>O.pbe-n-kjpaw_psl.0.1.UPF</pseudo_file>
      </species>
      <species name="H">
        <mass>1.007940000000000E+000</mass>
        <pseudo_file>H.pbe-rrkjus_psl.1.0.0.UPF</pseudo_file>
      </species>
    </atomic_species>
    <atomic_structure nat="3" alat="28.345891869386552" bravais_index="1">
      <atomic_positions>
        <atom name="O" index="1">
  8.025419650974656E-001  1.893648971888091E+000  2.225552819226879E+000
        </atom>
        <atom name="H" index="2">2.649448589023877E+000  1.849057772399800E+000  2.146246740130446E+000</atom>
        <atom name="H" index="3">2.730186854797300E-001  1.020735346686912E+000  6.836581302036492E-001</atom>
      </atomic_positions>
      <cell>
        <a1>2.834589186938655E+001  0.000000000000000E+000  0.000000000000000E+000</a1>
        <a2>0.000000000000000E+000  2.834589186938655E+001  0.000000000000000E+000</a2>
        <a3>0.000000000000000E+000  0.000000000000000E+000  2.834589186938655E+001</a3>
      </cell>
    </atomic_structure>
    <symmetries>
      <nsym>1</nsym>
      <nrot>48</nrot>
      <space_group>0</space_group>
      <symmetry>
        <info name="identity" class="E">crystal_symmetry</info>
        <rotation rank="2" dims="           3           3">
  1.000000000000000E+000  0.000000000000000E+000  0.000000000000000E+000
  0.000000000000000E+000  1.000000000000000E+000  0.000000000000000E+000
  0.000000000000000E+000  0.000000000000000E+000  1.000000000000000E+000
        </rotation>
        <fractional_translation>
  0.000000000000000E+000  0.000000000000000E+000  0.000000000000000E+000
        </fractional_translation>
        <equivalent_atoms size="3" nat="3">
           1           2           3
        </equivalent_atoms>
      </symmetry>
      <symmetry>
        <info name="180 deg rotation - cart. axis [0,0,1]" class="not found">lattice_symmetry</info>
        <rotation rank="2" dims="           3           3">
 -1.000000000000000E+000  0.000000000000000E+000  0.000000000000000E+000
  0.000000000000000E+000 -1.000000000000000E+000  0.000000000000000E+000
  0.000000000000000E+000  0.000000000000000E+000  1.000000000000000E+000
        </rotation>
      </symmetry>
      <symmetry>
        <info name="180 deg rotation - cart. axis [0,1,0]" class="not found">lattice_symmetry</info>
        <rotation rank="2" dims="           3           3">
 -1.000000000000000E+000  0.000000000000000E+000  0.000000000000000E+000
  0.000000000000000E+000  1.000000000000000E+000  0.000000000000000E+000
  0.000000000000000E+000  0.000000000000000E+000 -1.000000000000000E+000
        </rotation>
      </symmetry>
      <symmetry>
        <info name="180 deg rotation - cart. axis [1,0,0]" class="not found">lattice_symmetry</info>
        <rotation rank="2" dims="           3           3">
  1.000000000000000E+000  0.000000000000000E+000  0.000000000000000E+000
  0.000000000000000E+000 -1.000000000000000E+000  0.000000000000000E+000
  0.000000000000000E+000  0.000000000000000E+000 -1.000000000000000E+000
        </rotation>
      </symmetry>
      <symmetry>
        <info name="180 deg rotation - cart. axis [1,1,0]" class="not found">lattice_symmetry</info>
        <rotation rank="2" dims="           3           3">
  0.000000000000000E+000  1.000000000000000E+000  0.000000000000000E+000
  1.000000000000000E+000  0.000000000000000E+000  0.000000000000000E+000
  0.000000000000000E+000  0.000000000000000E+000 -1.000000000000000E+000
        </rotation>
      </symmetry>
      <symmetry>
        <info name="180 deg rotation - cart. axis [1,-1,0]" class="not found">lattice_symmetry</info>
        <rotation rank="2" dims="           3           3">
  0.000000000000000E+000 -1.000000000000000E+000  0.000000000000000E+000
 -1.000000000000000E+000  0.000000000000000E+000  0.000000000000000E+000
  0.000000000000000E+000  0.000000000000000E+000 -1.000000000000000E+000
        </rotation>
      </symmetry>
      <symmetry>
        <info name=" 90 deg rotation - cart. axis [0,0,-1]" class="not found">lattice_symmetry</info>
        <rotation rank="2" dims="           3           3">
  0.000000000000000E+000  1.000000000000000E+000  0.000000000000000E+000
 -1.000000000000000E+000  0.000000000000000E+000  0.000000000000000E+000
  0.000000000000000E+000  0.000000000000000E+000  1.000000000000000E+000
        </rotation>
      </symmetry>
      <symmetry>
        <info name=" 90 deg rotation - cart. axis [0,0,1]" class="not found">lattice_symmetry</info>
        <rotation rank="2" dims="           3           3">
  0.000000000000000E+000 -1.000000000000000E+000  0.000000000000000E+000
  1.000000000000000E+000  0.000000000000000E+000  0.000000000000000E+000
  0.000000000000000E+000  0.000000000000000E+000  1.000000000000000E+000
        </rotation>
      </symmetry>
      <symmetry>
        <info name="180 deg rotation - cart. axis [1,0,1]" class="not found">lattice_symmetry</info>
        <rotation rank="2" dims="           3           3">
  0.000000000000000E+000  0.000000000000000E+000  1.000000000000000E+000
  0.000000000000000E+000 -1.000000000000000E+000  0.000000000000000E+000
  1.000000000000000E+000  0.000000000000000E+000  0.000000000000000E+000
        </rotation>
      </symmetry>
      <symmetry>
        <info name="180 deg rotation - cart. axis [-1,0,1]" class="not found">lattice_symmetry</info>
        <rotation rank="2" dims="           3           3">
  0.000000000000000E+000  0.000000000000000E+000 -1.000000000000000E+000
  0.000000000000000E+000 -1.000000000000000E+000  0.000000000000000E+000
 -1.000000000000000E+000  0.000000000000000E+000  0.000000000000000E+000
        </rotation>
      </symmetry>
      <symmetry>
        <info name=" 90 deg rotation - cart. axis [0,1,0]" class="not found">lattice_symmetry</info>
        <rotation rank="2" dims="           3           3">
  0.000000000000000E+000  0.000000000000000E+000  1.000000000000000E+000
  0.000000000000000E+000  1.000000000000000E+000  0.000000000000000E+000
 -1.000000000000000E+000  0.000000000000000E+000  0.000000000000000E+000
        </rotation>
      </symmetry>
      <symmetry>
        <info name=" 90 deg rotation - cart. axis [0,-1,0]" class="not found">lattice_symmetry</info>
        <rotation rank="2" dims="           3           3">
  0.000000000000000E+000  0.000000000000000E+000 -1.000000000000000E+000
  0.000000000000000E+000  1.000000000000000E+000  0.000000000000000E+000
  1.000000000000000E+000  0.000000000000000E+000  0.000000000000000E+000
        </rotation>
      </symmetry>
      <symmetry>
        <info name="180 deg rotation - cart. axis [0,1,1]" class="not found">lattice_symmetry</info>
        <rotation rank="2" dims="           3           3">
 -1.000000000000000E+000  0.000000000000000E+000  0.000000000000000E+000
  0.000000000000000E+000  0.000000000000000E+000  1.000000000000000E+000
  0.000000000000000E+000  1.000000000000000E+000  0.000000000000000E+000
        </rotation>
      </symmetry>
      <symmetry>
        <info name="180 deg rotation - cart. axis [0,1,-1]" class="not found">lattice_symmetry</info>
        <rotation rank="2" dims="           3           3">
 -1.000000000000000E+000  0.000000000000000E+000  0.000000000000000E+000
  0.000000000000000E+000  0.000000000000000E+000 -1.000000000000000E+000
  0.000000000000000E+000 -1.000000000000000E+000  0.000000000000000E+000
        </rotation>
      </symmetry>
      <symmetry>
        <info name=" 90 deg rotation - cart. axis [-1,0,0]" class="not found">lattice_symmetry</info>
        <rotation rank="2" dims="           3           3">
  1.000000000000000E+000  0.000000000000000E+000  0.000000000000000E+000
  0.000000000000000E+000  0.000000000000000E+000  1.000000000000000E+000
  0.000000000000000E+000 -1.000000000000000E+000  0.000000000000000E+000
        </rotation>
      </symmetry>
      <symmetry>
        <info name=" 90 deg rotation - cart. axis [1,0,0]" class="not found">lattice_symmetry</info>
        <rotation rank="2" dims="           3           3">
  1.000000000000000E+000  0.000000000000000E+000  0.000000000000000E+000
  0.000000000000000E+000  0.000000000000000E+000 -1.000000000000000E+000
  0.000000000000000E+000  1.000000000000000E+000  0.000000000000000E+000
        </rotation>
      </symmetry>
      <symmetry>
        <info name="120 deg rotation - cart. axis [-1,-1,-1]" class="not found">lattice_symmetry</info>
        <rotation rank="2" dims="           3           3">
  0.000000000000000E+000  1.000000000000000E+000  0.000000000000000E+000
  0.000000000000000E+000  0.000000000000000E+000  1.000000000000000E+000
  1.000000000000000E+000  0.000000000000000E+000  0.000000000000000E+000
        </rotation>
      </symmetry>
      <symmetry>
        <info name="120 deg rotation - cart. axis [-1,1,1]" class="not found">lattice_symmetry</info>
        <rotation rank="2" dims="           3           3">
  0.000000000000000E+000 -1.000000000000000E+000  0.000000000000000E+000
  0.000000000000000E+000  0.000000000000000E+000  1.000000000000000E+000
 -1.000000000000000E+000  0.000000000000000E+000  0.000000000000000E+000
        </rotation>
      </symmetry>
      <symmetry>
        <info name="120 deg rotation - cart. axis [1,1,-1]" class="not found">lattice_symmetry</info>
        <rotation rank="2" dims="           3           3">
  0.000000000000000E+000  1.000000000000000E+000  0.000000000000000E+000
  0.000000000000000E+000  0.000000000000000E+000 -1.000000000000000E+000
 -1.000000000000000E+000  0.000000000000000E+000  0.000000000000000E+000
        </rotation>
      </symmetry>
      <symmetry>
        <info name="120 deg rotation - cart. axis [1,-1,1]" class="not found">lattice_symmetry</info>
        <rotation rank="2" dims="           3           3">
  0.000000000000000E+000 -1.000000000000000E+000  0.000000000000000E+000
  0.000000000000000E+000  0.000000000000000E+000 -1.000000000000000E+000
  1.000000000000000E+000  0.000000000000000E+000  0.000000000000000E+000
        </rotation>
      </symmetry>
      <symmetry>
        <info name="120 deg rotation - cart. axis [1,1,1]" class="not found">lattice_symmetry</info>
        <rotation rank="2" dims="           3           3">
  0.000000000000000E+000  0.000000000000000E+000  1.000000000000000E+000
  1.000000000000000E+000  0.000000000000000E+000  0.000000000000000E+000
  0.000000000000000E+000  1.000000000000000E+000  0.000000000000000E+000
        </rotation>
      </symmetry>
      <symmetry>
        <info name="120 deg rotation - cart. axis [-1,1,-1]" class="not found">lattice_symmetry</info>
        <rotation rank="2" dims="           3           3">
  0.000000000000000E+000  0.000000000000000E+000  1.000000000000000E+000
 -1.000000000000000E+000  0.000000000000000E+000  0.000000000000000E+000
  0.000000000000000E+000 -1.000000000000000E+000  0.000000000000000E+000
        </rotation>
      </symmetry>
      <symmetry>
        <info name="120 deg rotation - cart. axis [1,-1,-1]" class="not found">lattice_symmetry</info>
        <rotation rank="2" dims="           3           3">
  0.000000000000000E+000  0.000000000000000E+000 -1.000000000000000E+000
 -1.000000000000000E+000  0.000000000000000E+000  0.000000000000000E+000
  0.000000000000000E+000  1.000000000000000E+000  0.000000000000000E+000
        </rotation>
      </symmetry>
      <symmetry>
        <info name="120 deg rotation - cart. axis [-1,-1,1]" class="not found">lattice_symmetry</info>
        <rotation rank="2" dims="           3           3">
  0.000000000000000E+000  0.000000000000000E+000 -1.000000000000000E+000
  1.000000000000000E+000  0.000000000000000E+000  0.000000000000000E+000
  0.000000000000000E+000 -1.000000000000000E+000  0.000000000000000E+000
        </rotation>
      </symmetry>
      <symmetry>
        <info name="inversion" class="not found">lattice_symmetry</info>
        <rotation rank="2" dims="           3           3">
 -1.000000000000000E+000  0.000000000000000E+000  0.000000000000000E+000
  0.000000000000000E+000 -1.000000000000000E+000  0.000000000000000E+000
  0.000000000000000E+000  0.000000000000000E+000 -1.000000000000000E+000
        </rotation>
      </symmetry>
      <symmetry>
        <info name="inv. 180 deg rotation - cart. axis [0,0,1]" class="not found">lattice_symmetry</info>
        <rotation rank="2" dims="           3           3">
  1.000000000000000E+000  0.000000000000000E+000  0.000000000000000E+000
  0.000000000000000E+000  1.000000000000000E+000  0.000000000000000E+000
  0.000000000000000E+000  0.000000000000000E+000 -1.000000000000000E+000
        </rotation>
      </symmetry>
      <symmetry>
        <info name="inv. 180 deg rotation - cart. axis [0,1,0]" class="not found">lattice_symmetry</info>
        <rotation rank="2" dims="           3           3">
  1.000000000000000E+000  0.000000000000000E+000  0.000000000000000E+000
  0.000000000000000E+000 -1.000000000000000E+000  0.000000000000000E+000
  0.000000000000000E+000  0.000000000000000E+000  1.000000000000000E+000
        </rotation>
      </symmetry>
      <symmetry>
        <info name="inv. 180 deg rotation - cart. axis [1,0,0]" class="not found">lattice_symmetry</info>
        <rotation rank="2" dims="           3           3">
 -1.000000000000000E+000  0.000000000000000E+000  0.000000000000000E+000
  0.000000000000000E+000  1.000000000000000E+000  0.000000000000000E+000
  0.000000000000000E+000  0.000000000000000E+000  1.000000000000000E+000
        </rotation>
      </symmetry>
      <symmetry>
        <info name="inv. 180 deg rotation - cart. axis [1,1,0]" class="not found">lattice_symmetry</info>
        <rotation rank="2" dims="           3           3">
  0.000000000000000E+000 -1.000000000000000E+000  0.000000000000000E+000
 -1.000000000000000E+000  0.000000000000000E+000  0.000000000000000E+000
  0.000000000000000E+000  0.000000000000000E+000  1.000000000000000E+000
        </rotation>
      </symmetry>
      <symmetry>
        <info name="inv. 180 deg rotation - cart. axis [1,-1,0]" class="not found">lattice_symmetry</info>
        <rotation rank="2" dims="           3           3">
  0.000000000000000E+000  1.000000000000000E+000  0.000000000000000E+000
  1.000000000000000E+000  0.000000000000000E+000  0.000000000000000E+000
  0.000000000000000E+000  0.000000000000000E+000  1.000000000000000E+000
        </rotation>
      </symmetry>
      <symmetry>
        <info name="inv.  90 deg rotation - cart. axis [0,0,-1]" class="not found">lattice_symmetry</info>
        <rotation rank="2" dims="           3           3">
  0.000000000000000E+000 -1.000000000000000E+000  0.000000000000000E+000
  1.000000000000000E+000  0.000000000000000E+000  0.000000000000000E+000
  0.000000000000000E+000  0.000000000000000E+000 -1.000000000000000E+000
        </rotation>
      </symmetry>
      <symmetry>
        <info name="inv.  90 deg rotation - cart. axis [0,0,1]" class="not found">lattice_symmetry</info>
        <rotation rank="2" dims="           3           3">
  0.000000000000000E+000  1.000000000000000E+000  0.000000000000000E+000
 -1.000000000000000E+000  0.000000000000000E+000  0.000000000000000E+000
  0.000000000000000E+000  0.000000000000000E+000 -1.000000000000000E+000
        </rotation>
      </symmetry>
      <symmetry>
        <info name="inv. 180 deg rotation - cart. axis [1,0,1]" class="not found">lattice_symmetry</info>
        <rotation rank="2" dims="           3           3">
  0.000000000000000E+000  0.000000000000000E+000 -1.000000000000000E+000
  0.000000000000000E+000  1.000000000000000E+000  0.000000000000000E+000
 -1.000000000000000E+000  0.000000000000000E+000  0.000000000000000E+000
        </rotation>
      </symmetry>
      <symmetry>
        <info name="inv. 180 deg rotation - cart. axis [-1,0,1]" class="not found">lattice_symmetry</info>
        <rotation rank="2" dims="           3           3">
  0.000000000000000E+000  0.000000000000000E+000  1.000000000000000E+000
  0.000000000000000E+000  1.000000000000000E+000  0.000000000000000E+000
  1.000000000000000E+000  0.000000000000000E+000  0.000000000000000E+000
        </rotation>
      </symmetry>
      <symmetry>
        <info name="inv.  90 deg rotation - cart. axis [0,1,0]" class="not found">lattice_symmetry</info>
        <rotation rank="2" dims="           3           3">
  0.000000000000000E+000  0.000000000000000E+000 -1.000000000000000E+000
  0.000000000000000E+000 -1.000000000000000E+000  0.000000000000000E+000
  1.000000000000000E+000  0.000000000000000E+000  0.000000000000000E+000
        </rotation>
      </symmetry>
      <symmetry>
        <info name="inv.  90 deg rotation - cart. axis [0,-1,0]" class="not found">lattice_symmetry</info>
        <rotation rank="2" dims="           3           3">
  0.000000000000000E+000  0.000000000000000E+000  1.000000000000000E+000
  0.000000000000000E+000 -1.000000000000000E+000  0.000000000000000E+000
 -1.000000000000000E+000  0.000000000000000E+000  0.000000000000000E+000
        </rotation>
      </symmetry>
      <symmetry>
        <info name="inv. 180 deg rotation - cart. axis [0,1,1]" class="not found">lattice_symmetry</info>
        <rotation rank="2" dims="           3           3">
  1.000000000000000E+000  0.000000000000000E+000  0.000000000000000E+000
  0.000000000000000E+000  0.000000000000000E+000 -1.000000000000000E+000
  0.000000000000000E+000 -1.000000000000000E+000  0.000000000000000E+000
        </rotation>
      </symmetry>
      <symmetry>
        <info name="inv. 180 deg rotation - cart. axis [0,1,-1]" class="not found">lattice_symmetry</info>
        <rotation rank="2" dims="           3           3">
  1.000000000000000E+000  0.000000000000000E+000  0.000000000000000E+000
  0.000000000000000E+000  0.000000000000000E+000  1.000000000000000E+000
  0.000000000000000E+000  1.000000000000000E+000  0.000000000000000E+000
        </rotation>
      </symmetry>
      <symmetry>
        <info name="inv.  90 deg rotation - cart. axis [-1,0,0]" class="not found">lattice_symmetry</info>
        <rotation rank="2" dims="           3           3">
 -1.000000000000000E+000  0.000000000000000E+000  0.000000000000000E+000
  0.000000000000000E+000  0.000000000000000E+000 -1.000000000000000E+000
  0.000000000000000E+000  1.000000000000000E+000  0.000000000000000E+000
        </rotation>
      </symmetry>
      <symmetry>
        <info name="inv.  90 deg rotation - cart. axis [1,0,0]" class="not found">lattice_symmetry</info>
        <rotation rank="2" dims="           3           3">
 -1.000000000000000E+000  0.000000000000000E+000  0.000000000000000E+000
  0.000000000000000E+000  0.000000000000000E+000  1.000000000000000E+000
  0.000000000000000E+000 -1.000000000000000E+000  0.000000000000000E+000
        </rotation>
      </symmetry>
      <symmetry>
        <info name="inv. 120 deg rotation - cart. axis [-1,-1,-1]" class="not found">lattice_symmetry</info>
        <rotation rank="2" dims="           3           3">
  0.000000000000000E+000 -1.000000000000000E+000  0.000000000000000E+000
  0.000000000000000E+000  0.000000000000000E+000 -1.000000000000000E+000
 -1.000000000000000E+000  0.000000000000000E+000  0.000000000000000E+000
        </rotation>
      </symmetry>
      <symmetry>
        <info name="inv. 120 deg rotation - cart. axis [-1,1,1]" class="not found">lattice_symmetry</info>
        <rotation rank="2" dims="           3           3">
  0.000000000000000E+000  1.000000000000000E+000  0.000000000000000E+000
  0.000000000000000E+000  0.000000000000000E+000 -1.000000000000000E+000
  1.000000000000000E+000  0.000000000000000E+000  0.000000000000000E+000
        </rotation>
      </symmetry>
      <symmetry>
        <info name="inv. 120 deg rotation - cart. axis [1,1,-1]" class="not found">lattice_symmetry</info>
        <rotation rank="2" dims="           3           3">
  0.000000000000000E+000 -1.000000000000000E+000  0.000000000000000E+000
  0.000000000000000E+000  0.000000000000000E+000  1.000000000000000E+000
  1.000000000000000E+000  0.000000000000000E+000  0.000000000000000E+000
        </rotation>
      </symmetry>
      <symmetry>
        <info name="inv. 120 deg rotation - cart. axis [1,-1,1]" class="not found">lattice_symmetry</info>
        <rotation rank="2" dims="           3           3">
  0.000000000000000E+000  1.000000000000000E+000  0.000000000000000E+000
  0.000000000000000E+000  0.000000000000000E+000  1.000000000000000E+000
 -1.000000000000000E+000  0.000000000000000E+000  0.000000000000000E+000
        </rotation>
      </symmetry>
      <symmetry>
        <info name="inv. 120 deg rotation - cart. axis [1,1,1]" class="not found">lattice_symmetry</info>
        <rotation rank="2" dims="           3           3">
  0.000000000000000E+000  0.000000000000000E+000 -1.000000000000000E+000
 -1.000000000000000E+000  0.000000000000000E+000  0.000000000000000E+000
  0.000000000000000E+000 -1.000000000000000E+000  0.000000000000000E+000
        </rotation>
      </symmetry>
      <symmetry>
        <info name="inv. 120 deg rotation - cart. axis [-1,1,-1]" class="not found">lattice_symmetry</info>
        <rotation rank="2" dims="           3           3">
  0.000000000000000E+000  0.000000000000000E+000 -1.000000000000000E+000
  1.000000000000000E+000  0.000000000000000E+000  0.000000000000000E+000
  0.000000000000000E+000  1.000000000000000E+000  0.000000000000000E+000
        </rotation>
      </symmetry>
      <symmetry>
        <info name="inv. 120 deg rotation - cart. axis [1,-1,-1]" class="not found">lattice_symmetry</info>
        <rotation rank="2" dims="           3           3">
  0.000000000000000E+000  0.000000000000000E+000  1.000000000000000E+000
  1.000000000000000E+000  0.000000000000000E+000  0.000000000000000E+000
  0.000000000000000E+000 -1.000000000000000E+000  0.000000000000000E+000
        </rotation>
      </symmetry>
      <symmetry>
        <info name="inv. 120 deg rotation - cart. axis [-1,-1,1]" class="not found">lattice_symmetry</info>
        <rotation rank="2" dims="           3           3">
  0.000000000000000E+000  0.000000000000000E+000  1.000000000000000E+000
 -1.000000000000000E+000  0.000000000000000E+000  0.000000000000000E+000
  0.000000000000000E+000  1.000000000000000E+000  0.000000000000000E+000
        </rotation>
      </symmetry>
    </symmetries>
    <basis_set>
      <gamma_only>true</gamma_only>
      <ecutwfc>1.500000000000000E+001</ecutwfc>
      <ecutrho>6.000000000000000E+001</ecutrho>
      <fft_grid nr1="100" nr2="100" nr3="100"></fft_grid>
      <fft_smooth nr1="100" nr2="100" nr3="100"></fft_smooth>
      <fft_box nr1="100" nr2="100" nr3="100"></fft_box>
      <ngm>252944</ngm>
      <ngms>252944</ngms>
      <npwx>31539</npwx>
      <reciprocal_lattice>
        <b1>
  1.000000000000000E+000  0.000000000000000E+000  0.000000000000000E+000
        </b1>
        <b2>0.000000000000000E+000  1.000000000000000E+000  0.000000000000000E+000</b2>
        <b3>0.000000000000000E+000  0.000000000000000E+000  1.000000000000000E+000</b3>
      </reciprocal_lattice>
    </basis_set>
    <dft>
      <functional>PBE</functional>
    </dft>
    <magnetization>
      <lsda>false</lsda>
      <noncolin>false</noncolin>
      <spinorbit>false</spinorbit>
      <absolute>0.000000000000000E+000</absolute>
    </magnetization>
    <total_energy>
      <etot>-2.198468545540472E+001</etot>
      <eband>-4.030511212499176E+000</eband>
      <ehart>1.801317647863582E+001</ehart>
      <vtxc>-5.488483420298243E+000</vtxc>
      <etxc>-4.401331028004509E+000</etxc>
      <ewald>3.634309867773721E+000</ewald>
      <demet>1.737615422746113E-019</demet>
    </total_energy>
    <band_structure>
      <lsda>false</lsda>
      <noncolin>false</noncolin>
      <spinorbit>false</spinorbit>
      <nbnd>8</nbnd>
      <nelec>8.000000000000000E+000</nelec>
      <num_of_atomic_wfc>6</num_of_atomic_wfc>
      <wf_collected>true</wf_collected>
      <fermi_energy>-1.939292560233934E-001</fermi_energy>
      <starting_k_points>
        <nk>1</nk>
        <k_point weight="1.0000000000000000">0.000000000000000E+000  0.000000000000000E+000  0.000000000000000E+000</k_point>
      </starting_k_points>
      <nks>1</nks>
      <occupations_kind>smearing</occupations_kind>
      <smearing degauss="1.0000000000000000E-002">mv</smearing>
      <ks_energies>
        <k_point weight="2.0000000000000000">0.000000000000000E+000  0.000000000000000E+000  0.000000000000000E+000</k_point>
        <npw>31539</npw>
        <eigenvalues size="8">
 -9.311322370938280E-001 -4.768532015207321E-001 -3.428563331341596E-001
 -2.644138345008683E-001 -5.257461154877417E-002
 -2.903588410780099E-002 -1.913435074502528E-002 -1.486159566658187E-002
        </eigenvalues>
        <occupations size="8">
  1.000000000000000E+000  1.000000000000000E+000  1.000000000000000E+000
  1.000000000000000E+000  0.000000000000000E+000
  0.000000000000000E+000  0.000000000000000E+000  0.000000000000000E+000
        </occupations>
      </ks_energies>
    </band_structure>
    <forces rank="2" dims="           3           3">
  2.933750968339834E-008  4.639012079194125E-006  9.652194447241056E-005
 -3.617570358064769E-006 -5.254505344260721E-006  9.524991690917006E-006
  3.588232848381364E-006  6.154932650665894E-007 -1.060469361633276E-004
    </forces>
    <stress rank="2" dims="           3           3">
 -7.457377763580203E-006  8.394997106690246E-008  1.498689038721183E-007
  8.394997106690246E-008 -8.198200262546284E-006  3.492747125257142E-007
  1.498689038721183E-007  3.492747125257142E-007 -7.778292165848453E-006
    </stress>
  </output>
  <exit_status>0</exit_status>
  <timing_info>
    <total label="PWSCF">
      <cpu>3.272097000000000E+000</cpu>
      <wall>3.699396848678589E+000</wall>
    </total>
    <partial label="init_run" calls="1">
      <cpu>1.032430000000000E-001</cpu>
      <wall>1.223878860473633E-001</wall>
    </partial>
    <partial label="hinit0" calls="1">
      <cpu>1.066999999999999E-002</cpu>
      <wall>1.609897613525391E-002</wall>
    </partial>
    <partial label="init_vloc" calls="1">
      <cpu>1.932999999999990E-003</cpu>
      <wall>2.542018890380859E-003</wall>
    </partial>
    <partial label="init_us_1" calls="1">
      <cpu>4.142000000000007E-003</cpu>
      <wall>5.900859832763672E-003</wall>
    </partial>
    <partial label="fft" calls="434">
      <cpu>4.433530000000023E-001</cpu>
      <wall>4.977083206176758E-001</wall>
    </partial>
    <partial label="fft_scatter" calls="1299">
      <cpu>3.312209999999958E-001</cpu>
      <wall>3.831446170806885E-001</wall>
    </partial>
    <partial label="potinit" calls="1">
      <cpu>3.333700000000001E-002</cpu>
      <wall>4.041695594787598E-002</wall>
    </partial>
    <partial label="v_of_rho" calls="34">
      <cpu>7.959730000000005E-001</cpu>
      <wall>8.302600383758545E-001</wall>
    </partial>
    <partial label="v_xc" calls="46">
      <cpu>1.021072000000003E+000</cpu>
      <wall>1.054391622543335E+000</wall>
    </partial>
    <partial label="v_h" calls="34">
      <cpu>4.257199999999983E-002</cpu>
      <wall>4.975271224975586E-002</wall>
    </partial>
    <partial label="PAW_pot" calls="39">
      <cpu>3.305140000000000E-001</cpu>
      <wall>3.676476478576660E-001</wall>
    </partial>
    <partial label="newd" calls="34">
      <cpu>2.307370000000009E-001</cpu>
      <wall>2.415742874145508E-001</wall>
    </partial>
    <partial label="wfcinit" calls="1">
      <cpu>8.099999999999996E-003</cpu>
      <wall>1.020312309265137E-002</wall>
    </partial>
    <partial label="init_us_2" calls="68">
      <cpu>1.303599999999783E-002</cpu>
      <wall>1.404690742492676E-002</wall>
    </partial>
    <partial label="wfcinit:atom" calls="1">
      <cpu>2.499999999999725E-005</cpu>
      <wall>1.361370086669922E-004</wall>
    </partial>
    <partial label="atomic_wfc" calls="1">
      <cpu>2.499999999999725E-005</cpu>
      <wall>1.342296600341797E-004</wall>
    </partial>
    <partial label="wfcinit:wfcr" calls="1">
      <cpu>7.980999999999988E-003</cpu>
      <wall>8.279085159301758E-003</wall>
    </partial>
    <partial label="wfcrot" calls="1">
      <cpu>7.980999999999988E-003</cpu>
      <wall>8.278131484985352E-003</wall>
    </partial>
    <partial label="rotwfcg" calls="1">
      <cpu>7.979999999999987E-003</cpu>
      <wall>8.275032043457031E-003</wall>
    </partial>
    <partial label="rotwfcg:hpsi" calls="1">
      <cpu>7.393999999999984E-003</cpu>
      <wall>7.498979568481445E-003</wall>
    </partial>
    <partial label="h_psi_bgrp" calls="116">
      <cpu>4.195620000000018E-001</cpu>
      <wall>4.706628322601318E-001</wall>
    </partial>
    <partial label="h_psi" calls="116">
      <cpu>4.194319999999996E-001</cpu>
      <wall>4.705567359924316E-001</wall>
    </partial>
    <partial label="h_psi:pot" calls="116">
      <cpu>4.180890000000006E-001</cpu>
      <wall>4.691352844238281E-001</wall>
    </partial>
    <partial label="vloc_psi" calls="116">
      <cpu>3.899729999999995E-001</cpu>
      <wall>4.390478134155273E-001</wall>
    </partial>
    <partial label="fftw" calls="834">
      <cpu>4.213390000000010E-001</cpu>
      <wall>4.751465320587158E-001</wall>
    </partial>
    <partial label="h_psi:calbec" calls="116">
      <cpu>2.394300000000005E-002</cpu>
      <wall>2.558898925781250E-002</wall>
    </partial>
    <partial label="calbec" calls="182">
      <cpu>3.904399999999786E-002</cpu>
      <wall>4.256963729858398E-002</wall>
    </partial>
    <partial label="add_vuspsi" calls="116">
      <cpu>3.898000000000401E-003</cpu>
      <wall>4.198551177978516E-003</wall>
    </partial>
    <partial label="rotwfcg:hc" calls="1">
      <cpu>4.930000000000212E-004</cpu>
      <wall>5.228519439697266E-004</wall>
    </partial>
    <partial label="s_psi_bgrp" calls="116">
      <cpu>5.202999999999847E-003</cpu>
      <wall>5.635023117065430E-003</wall>
    </partial>
    <partial label="s_psi" calls="116">
      <cpu>3.746000000000027E-003</cpu>
      <wall>4.042863845825195E-003</wall>
    </partial>
    <partial label="rotwfcg:diag" calls="1">
      <cpu>9.199999999998099E-005</cpu>
      <wall>9.179115295410156E-005</wall>
    </partial>
    <partial label="rdiaghg" calls="107">
      <cpu>6.417999999999591E-003</cpu>
      <wall>6.661415100097656E-003</wall>
    </partial>
    <partial label="rotwfcg:evc" calls="1">
      <cpu>0.000000000000000E+000</cpu>
      <wall>1.568794250488281E-004</wall>
    </partial>
    <partial label="electrons" calls="6">
      <cpu>2.051830000000000E+000</cpu>
      <wall>2.283250570297241E+000</wall>
    </partial>
    <partial label="c_bands" calls="31">
      <cpu>4.980310000000001E-001</cpu>
      <wall>5.531334877014160E-001</wall>
    </partial>
    <partial label="regterg" calls="31">
      <cpu>4.855380000000005E-001</cpu>
      <wall>5.396602153778076E-001</wall>
    </partial>
    <partial label="regterg:init" calls="31">
      <cpu>1.014799999999916E-002</cpu>
      <wall>1.017808914184570E-002</wall>
    </partial>
    <partial label="regterg:upda" calls="84">
      <cpu>4.542000000000268E-003</cpu>
      <wall>4.747390747070312E-003</wall>
    </partial>
    <partial label="g_psi" calls="84">
      <cpu>1.325000000001353E-003</cpu>
      <wall>1.399755477905273E-003</wall>
    </partial>
    <partial label="regterg:over" calls="84">
      <cpu>2.971099999999893E-002</cpu>
      <wall>3.063797950744629E-002</wall>
    </partial>
    <partial label="regterg:diag" calls="106">
      <cpu>6.485000000000518E-003</cpu>
      <wall>6.696701049804688E-003</wall>
    </partial>
    <partial label="regterg:last" calls="71">
      <cpu>1.000999999999985E-002</cpu>
      <wall>1.091647148132324E-002</wall>
    </partial>
    <partial label="sum_band" calls="31">
      <cpu>3.434879999999989E-001</cpu>
      <wall>3.666663169860840E-001</wall>
    </partial>
    <partial label="sum_band:wei" calls="31">
      <cpu>1.340000000000785E-004</cpu>
      <wall>1.456737518310547E-004</wall>
    </partial>
    <partial label="sum_band:loo" calls="31">
      <cpu>8.021300000000053E-002</cpu>
      <wall>9.006452560424805E-002</wall>
    </partial>
    <partial label="sum_band:buf" calls="31">
      <cpu>1.899999999999125E-005</cpu>
      <wall>1.192092895507812E-005</wall>
    </partial>
    <partial label="sum_band:ini" calls="31">
      <cpu>5.894999999998429E-003</cpu>
      <wall>6.181240081787109E-003</wall>
    </partial>
    <partial label="sum_band:cal" calls="36">
      <cpu>8.628999999999998E-003</cpu>
      <wall>9.842395782470703E-003</wall>
    </partial>
    <partial label="sum_band:bec" calls="36">
      <cpu>8.400000000063912E-005</cpu>
      <wall>1.001358032226562E-004</wall>
    </partial>
    <partial label="ffts" calls="31">
      <cpu>3.166400000000102E-002</cpu>
      <wall>3.633451461791992E-002</wall>
    </partial>
    <partial label="addusdens" calls="31">
      <cpu>1.926819999999996E-001</cpu>
      <wall>1.959624290466309E-001</wall>
    </partial>
    <partial label="addusd:skk" calls="62">
      <cpu>2.680999999999045E-003</cpu>
      <wall>2.778291702270508E-003</wall>
    </partial>
    <partial label="sum_band:sym" calls="31">
      <cpu>3.396000000000088E-002</cpu>
      <wall>3.877687454223633E-002</wall>
    </partial>
    <partial label="mix_rho" calls="31">
      <cpu>4.369500000000137E-002</cpu>
      <wall>4.755353927612305E-002</wall>
    </partial>
    <partial label="high_freq_mi" calls="22">
      <cpu>2.007999999999122E-003</cpu>
      <wall>2.036094665527344E-003</wall>
    </partial>
    <partial label="ions" calls="6">
      <cpu>7.975879999999997E-001</cpu>
      <wall>8.336193561553955E-001</wall>
    </partial>
    <partial label="forces" calls="6">
      <cpu>2.574500000000004E-001</cpu>
      <wall>2.618439197540283E-001</wall>
    </partial>
    <partial label="frc_us" calls="6">
      <cpu>5.876500000000018E-002</cpu>
      <wall>6.015801429748535E-002</wall>
    </partial>
    <partial label="frc_lc" calls="6">
      <cpu>1.744100000000026E-002</cpu>
      <wall>1.845240592956543E-002</wall>
    </partial>
    <partial label="frc_cc" calls="6">
      <cpu>1.481470000000003E-001</cpu>
      <wall>1.498551368713379E-001</wall>
    </partial>
    <partial label="frc_scc" calls="6">
      <cpu>2.062499999999989E-002</cpu>
      <wall>2.067375183105469E-002</wall>
    </partial>
    <partial label="stress" calls="6">
      <cpu>5.211739999999998E-001</cpu>
      <wall>5.348038673400879E-001</wall>
    </partial>
    <partial label="update_pot" calls="5">
      <cpu>1.749190000000005E-001</cpu>
      <wall>1.916389465332031E-001</wall>
    </partial>
    <partial label="compute_becs" calls="5">
      <cpu>2.533000000000118E-003</cpu>
      <wall>2.535820007324219E-003</wall>
    </partial>
  </timing_info>
  <closed DATE="15 Mar 2025" TIME="23:22: 4"></closed>
</qes:espresso>
